Workbook

Sheet CQ Catalogue
A1: FFOnto – Competency Question catalogue derived from ForestFire-VQA (English)
A2: Each dataset question is an INSTANCE of one CQ template below. Counts are formulas over the 'Question Mapping' sheet. Mapping was auto-assigned by keyword rules — review the 'CQ' column there and edit it; counts update automatically.
A4: CQ ID | B4: Layer | C4: Competency question (template) | D4: How the KG answers it | E4: Key ontology terms (indicative) | F4: # dataset questions | G4: % of dataset | H4: Example dataset questions
A5: CQ01 | B5: A. Multimodal record & provenance | C5: Which data records (image, audio, weather row) exist for fire event E, in which modalities, and which records share the same event? | D5: KG – direct (from JSON/CSV) | E5: ffo:FireEvent, ffo:DataRecord {ImageRecord, AudioRecord, WeatherRecord}, ffo:aboutEvent, ffo:hasModality | F5: =COUNTIF('Question Mapping'!$F$2:$F$1005,A5) -> 7 | G5: =F5/$F$32 -> 0.0069721116 | H5: • Is there an image available for this fire event? • Is there an audio clip available for this event? • Is the event "ev_32d96b02d3dd" attached to the image? • Do the image and audio share this fire event?
A6: CQ02 | B6: A. Multimodal record & provenance | C6: What metadata is recorded for record R (id/uuid, URI, checksum, license, size, resolution, bands, source/device, CRS, georeference, footprint, capture time, duration), and which fields are missing? | D6: KG – direct + SHACL completeness check | E6: prov:Entity, dcterms:license, ffo:checksum, geo:hasGeometry, time:inXSDDateTime, sosa:Sensor | F6: =COUNTIF('Question Mapping'!$F$2:$F$1005,A6) -> 24 | G6: =F6/$F$32 -> 0.023904382 | H6: • Is cloud cover quality metadata present? • What is the image’s image_id? • Is blur quality metadata present? • What is the image resolution in pixels (width × height)?
A7: CQ03 | B7: A. Multimodal record & provenance | C7: Which model (name, version, provenance URL) produced annotation A, from which label source (caption / zero-shot / detector / human), and was it human-validated? | D7: KG – direct | E7: prov:Activity (ModelRun), prov:SoftwareAgent (Model), ffo:labelSource, prov:wasAttributedTo | F7: =COUNTIF('Question Mapping'!$F$2:$F$1005,A7) -> 9 | G7: =F7/$F$32 -> 0.0089641434 | H7: • Which vision model produced the scores (name/version)? • Which caption model produced the caption? • What is the label_source (e.g., caption vs. detector)? • Is the model version recorded for audit?
A8: CQ04 | B8: A. Multimodal record & provenance | C8: What label/score/confidence did model M assign to class C for record R (fire, smoke, no-fire; audio mean/max confidence; top-k labels; severity)? | D8: KG – direct | E8: sosa:Observation, sosa:hasResult, ffo:confidence, ffo:predictedClass | F8: =COUNTIF('Question Mapping'!$F$2:$F$1005,A8) -> 6 | G8: =F8/$F$32 -> 0.0059760956 | H8: • What is the model’s fire probability score for this image? • What is the smoke score (zshot_scores.smoke)? • What is the fire score (zshot_scores.fire)? • What is the no-fire score?
A9: CQ05 | B9: A. Multimodal record & provenance | C9: Which threshold applies to class C, does the score exceed it, and what decision/alert status follows for R or E? | D9: KG – rule (SPARQL / SHACL-AF) | E9: ffo:Threshold, ffo:thresholdValue, ffo:Decision, ffo:AlertStatus | F9: =COUNTIF('Question Mapping'!$F$2:$F$1005,A9) -> 13 | G9: =F9/$F$32 -> 0.012948207 | H9: • Is smoke present above the detection threshold in this frame? • What is the configured fire_threshold? • What is the configured smoke_threshold? • Is the smoke score above the smoke threshold?
A10: CQ06 | B10: A. Multimodal record & provenance | C10: What does the auto-caption of R say, and does it mention concept K (smoke, fire, aircraft, water, terrain, daytime, windy, dense smoke)? | D10: KG – direct (caption text) + concept tagging | E10: ffo:Caption, ffo:mentionsConcept → SKOS concept | F10: =COUNTIF('Question Mapping'!$F$2:$F$1005,A10) -> 10 | G10: =F10/$F$32 -> 0.0099601594 | H10: • Does the auto-caption mention smoke? • Does the caption mention fire/flames? • Does the caption mention aircraft/plane/helicopter? • Does the caption mention terrain features (ridge/mountain)?
A11: CQ07 | B11: A. Multimodal record & provenance | C11: Are the records of event E consistent across modalities (caption vs scores, audio vs image, weather vs visual smoke), and are all fields required for alerting present? | D11: KG – rule (cross-modal) | E11: ffo:ConsistencyCheck, ffo:conflictsWith, SHACL shape for alert readiness | F11: =COUNTIF('Question Mapping'!$F$2:$F$1005,A11) -> 7 | G11: =F11/$F$32 -> 0.0069721116 | H11: • Is there any conflict between caption (“smoke”) and model fire score (below threshold)? • Are timestamps present in both records (for temporal pairing)? • Is the caption consistent with the vision scores (smoke>fire)? • Does zero rain align with observed smoke in the image?
A12: CQ08 | B12: B. Weather & fire danger | C12: What weather values (temperature, RH, wind, rain) were observed at site S on date D? | D12: KG – direct (tabular) | E12: sosa:Observation, ffo:AirTemperature, ffo:RelativeHumidity, ffo:WindSpeed, ffo:Precipitation, qudt:unit | F12: =COUNTIF('Question Mapping'!$F$2:$F$1005,A12) -> 14 | G12: =F12/$F$32 -> 0.013944223 | H12: • What is the current air temperature (°C) at the incident site? • What is the current relative humidity (%)? • What is the current wind speed (km/h)? • Has any precipitation (mm) been recorded today?
A13: CQ09 | B13: B. Weather & fire danger | C13: What Fire Weather Index components (FFMC, DMC, DC, ISI, BUI, FWI), fire occurrence and burned area are recorded for site S / grid cell on date D, and how do detections trend over time? | D13: KG – direct (tabular) | E13: ffo:FWIComponent {FFMC…FWI}, ffo:fireOccurred, ffo:burnedArea, ffo:GridCell | F13: =COUNTIF('Question Mapping'!$F$2:$F$1005,A13) -> 17 | G13: =F13/$F$32 -> 0.016932271 | H13: • What’s the current size of the fire (acres/ha)? • Are detections increasing or decreasing compared to the previous update? • What are today’s FFMC and ISI values? • What are today’s DMC and DC values?
A14: CQ10 | B14: B. Weather & fire danger | C14: Do weather/FWI values exceed rule thresholds implying an operational condition (elevated danger, reduced aerial-drop effectiveness, heat stress, favour direct vs indirect attack, mop-up conditions)? | D14: KG – rule (thresholds as data) | E14: ffo:DangerRule, ffo:indicatesCondition → SKOS concept | F14: =COUNTIF('Question Mapping'!$F$2:$F$1005,A14) -> 10 | G14: =F14/$F$32 -> 0.0099601594 | H14: • Is wind speed high enough to reduce aerial drop effectiveness? • Does low relative humidity favor direct attack with hand tools today? • Has any rain today improved conditions for mop-up? • Do ISI/FFMC values indicate rapid fine-fuel spread (favor indirect tactics)?
A15: CQ11 | B15: C. Scene perception (image) | C15: Which fire phenomena (flame front, spot fire, crown fire, torching, smouldering, hotspot, pyrocumulus, fire cluster) are present in scene S, and how many? | D15: KG – needs scene-graph extraction | E15: ffo:FirePhenomenon (SKOS-typed), ffo:depicts, ffo:count | F15: =COUNTIF('Question Mapping'!$F$2:$F$1005,A15) -> 10 | G15: =F15/$F$32 -> 0.0099601594 | H15: • Are flame fronts visible from the camera location? • Are multiple distinct flame fronts visible? • Are spot fires visible ahead of the main flames (frame-relative)? • Are structures or vegetation smoldering without open flames?
A16: CQ12 | B16: C. Scene perception (image) | C16: What are the properties of the smoke in scene S (colour, density/thickness, plume height and direction, layers, obscuration)? | D16: KG – needs scene-graph extraction | E16: ffo:Smoke, ffo:hasColour, ffo:hasDensity, ffo:plumeDirection (SKOS value sets) | F16: =COUNTIF('Question Mapping'!$F$2:$F$1005,A16) -> 18 | G16: =F16/$F$32 -> 0.017928287 | H16: • Where is smoke production heaviest ? • Does the smoke appear light, gray, or dark? • Is the smoke plume rising vertically or drifting horizontally? • Is scene visibility low, medium, or high due to smoke?
... A31: OOS | B31: F. Out of KG scope | C31: General-knowledge / public-guidance question not grounded in a dataset record (definitions, how-to, policy, health advice, technology). | D31: Text RAG over documents (optionally concept definitions as skos:definition) | E31: — (not modelled as classes/properties) | F31: =COUNTIF('Question Mapping'!$F$2:$F$1005,A31) -> 291 | G31: =F31/$F$32 -> 0.28984064 | H31: • Is the explosion confidence above the alert threshold for crew safety? • What should drivers do if caught in heavy smoke on the road? • When should you shelter in place instead of evacuating? • Can you outrun a wildfire on foot or by car?
E32: Total | F32: =SUM(F5:F31) -> 1004

Sheet Question Mapping
A1: Sheet | B1: Source | C1: Modality | D1: Question | E1: Answer (original) | F1: CQ | G1: Layer | H1: How answered
A2: Situation Awareness | B2: {"X": 2, "Y": 2, "month": "aug", "day": "tue", "FFMC": 94.8, "DMC": 108.3, "DC": | C2: Tabular (weather/FWI) | D2: What’s the current size of the fire (acres/ha)? | E2: 1.07 (2.64 acres) based on the latest perimeter snapshot. | F2: CQ09 | G2: B. Weather & fire danger | H2: KG – direct (tabular)
A3: Situation Awareness | B3: forest_fire_001.jpg | C3: Image | D3: Is the fire primarily a surface/ground fire or crown fire ? | E3: Primarily a surface/ground fire with intermittent torching. | F3: CQ13 | G3: C. Scene perception (image) | H3: KG – extraction + rule
A4: Situation Awareness | B4: forest_fire_002.jpg | C4: Image | D4: Where is smoke production heaviest ? | E4: Heaviest on the NE flank near the ridgeline. | F4: CQ12 | G4: C. Scene perception (image) | H4: KG – needs scene-graph extraction
A5: Situation Awareness | B5: forest_fire_003.jpg | C5: Image | D5: Are flame fronts visible from the camera location? | E5: Yes—two active flame fronts are visible from this camera. | F5: CQ11 | G5: C. Scene perception (image) | H5: KG – needs scene-graph extraction
A6: Situation Awareness | B6: {"X": 2, "Y": 2, "month": "aug", "day": "tue", "FFMC": 94.8, "DMC": 108.3, "DC": | C6: Tabular (weather/FWI) | D6: Are detections increasing or decreasing compared to the previous update? | E6: Increasing compared to the previous update. | F6: CQ09 | G6: B. Weather & fire danger | H6: KG – direct (tabular)
A7: Situation Awareness | B7: {"day": 27, "month": 8, "year": 2012, "Temperature": 33, "RH": 82, "Ws": 21, "Ra | C7: Tabular (weather/FWI) | D7: Is wind speed high enough to reduce aerial drop effectiveness? | E7: Yes—~21 km/h sustained with gusts; drift/evap likely. | F7: CQ10 | G7: B. Weather & fire danger | H7: KG – rule (thresholds as data)
A8: Situation Awareness | B8: {"day": 27, "month": 8, "year": 2012, "Temperature": 33, "RH": 82, "Ws": 21, "Ra | C8: Tabular (weather/FWI) | D8: Does low relative humidity favor direct attack with hand tools today? | E8: No — relative humidity is 82%, which is high and does not favor direct attack with hand tools. | F8: CQ10 | G8: B. Weather & fire danger | H8: KG – rule (thresholds as data)
A9: Situation Awareness | B9: {"day": 27, "month": 8, "year": 2012, "Temperature": 33, "RH": 82, "Ws": 21, "Ra | C9: Tabular (weather/FWI) | D9: Has any rain today improved conditions for mop-up? | E9: No—0.0 mm today; mop-up remains challenging. | F9: CQ10 | G9: B. Weather & fire danger | H9: KG – rule (thresholds as data)
A10: Situation Awareness | B10: {"day": 27, "month": 8, "year": 2012, "Temperature": 33, "RH": 82, "Ws": 21, "Ra | C10: Tabular (weather/FWI) | D10: Do ISI/FFMC values indicate rapid fine-fuel spread (favor indirect tactics)? | E10: No — today’s FFMC 84.9 and ISI 4.4 indicate only moderate spread potential, not rapid fine-fuel spread, so indirect tactics are not strongly favored. | F10: CQ10 | G10: B. Weather & fire danger | H10: KG – rule (thresholds as data)
A11: Situation Awareness | B11: forest_fire_004.jpg | C11: Image | D11: Is smoke present above the detection threshold in this frame? | E11: Yes—smoke score 0.78 exceeds the 0.60 threshold. | F11: CQ05 | G11: A. Multimodal record & provenance | H11: KG – rule (SPARQL / SHACL-AF)
A12: Situation Awareness | B12: forest_fire_005.jpg | C12: Image | D12: What is the model’s fire probability score for this image? | E12: Fire probability 0.34 (below the 0.55 fire threshold). | F12: CQ04 | G12: A. Multimodal record & provenance | H12: KG – direct
... A1005: Environmental Assesment | B1005: forest_fire_142.jpg | C1005: Image | D1005: If a fire occurred here, what would be the most immediate environmental impact? | E1005: Loss of tree cover, destruction of wildlife habitat, and release of carbon into the atmosphere would occur rapidly. | F1005: CQ24 | G1005: E. Derived risk & recommendation | H1005: KG – rule / reasoning over CQ11–23

Sheet Summary
A1: Questions by modality and answer layer
A3: Layer | B3: Image | C3: Audio | D3: Tabular (weather/FWI) | E3: General knowledge (no record) | F3: Total
A4: A. Multimodal record & provenance | B4: =COUNTIFS('Question Mapping'!$G$2:$G$1005,$A4,'Question Mapping'!$C$2:$C$1005,B$3) -> 50 | C4: =COUNTIFS('Question Mapping'!$G$2:$G$1005,$A4,'Question Mapping'!$C$2:$C$1005,C$3) -> 24 | D4: =COUNTIFS('Question Mapping'!$G$2:$G$1005,$A4,'Question Mapping'!$C$2:$C$1005,D$3) -> 2 | E4: =COUNTIFS('Question Mapping'!$G$2:$G$1005,$A4,'Question Mapping'!$C$2:$C$1005,E$3) -> 0 | F4: =SUM(B4:E4) -> 76
A5: B. Weather & fire danger | B5: =COUNTIFS('Question Mapping'!$G$2:$G$1005,$A5,'Question Mapping'!$C$2:$C$1005,B$3) -> 1 | C5: =COUNTIFS('Question Mapping'!$G$2:$G$1005,$A5,'Question Mapping'!$C$2:$C$1005,C$3) -> 0 | D5: =COUNTIFS('Question Mapping'!$G$2:$G$1005,$A5,'Question Mapping'!$C$2:$C$1005,D$3) -> 40 | E5: =COUNTIFS('Question Mapping'!$G$2:$G$1005,$A5,'Question Mapping'!$C$2:$C$1005,E$3) -> 0 | F5: =SUM(B5:E5) -> 41
A6: C. Scene perception (image) | B6: =COUNTIFS('Question Mapping'!$G$2:$G$1005,$A6,'Question Mapping'!$C$2:$C$1005,B$3) -> 419 | C6: =COUNTIFS('Question Mapping'!$G$2:$G$1005,$A6,'Question Mapping'!$C$2:$C$1005,C$3) -> 0 | D6: =COUNTIFS('Question Mapping'!$G$2:$G$1005,$A6,'Question Mapping'!$C$2:$C$1005,D$3) -> 0 | E6: =COUNTIFS('Question Mapping'!$G$2:$G$1005,$A6,'Question Mapping'!$C$2:$C$1005,E$3) -> 0 | F6: =SUM(B6:E6) -> 419
A7: D. Audio | B7: =COUNTIFS('Question Mapping'!$G$2:$G$1005,$A7,'Question Mapping'!$C$2:$C$1005,B$3) -> 0 | C7: =COUNTIFS('Question Mapping'!$G$2:$G$1005,$A7,'Question Mapping'!$C$2:$C$1005,C$3) -> 16 | D7: =COUNTIFS('Question Mapping'!$G$2:$G$1005,$A7,'Question Mapping'!$C$2:$C$1005,D$3) -> 0 | E7: =COUNTIFS('Question Mapping'!$G$2:$G$1005,$A7,'Question Mapping'!$C$2:$C$1005,E$3) -> 0 | F7: =SUM(B7:E7) -> 16
A8: E. Derived risk & recommendation | B8: =COUNTIFS('Question Mapping'!$G$2:$G$1005,$A8,'Question Mapping'!$C$2:$C$1005,B$3) -> 160 | C8: =COUNTIFS('Question Mapping'!$G$2:$G$1005,$A8,'Question Mapping'!$C$2:$C$1005,C$3) -> 1 | D8: =COUNTIFS('Question Mapping'!$G$2:$G$1005,$A8,'Question Mapping'!$C$2:$C$1005,D$3) -> 0 | E8: =COUNTIFS('Question Mapping'!$G$2:$G$1005,$A8,'Question Mapping'!$C$2:$C$1005,E$3) -> 0 | F8: =SUM(B8:E8) -> 161
A9: F. Out of KG scope | B9: =COUNTIFS('Question Mapping'!$G$2:$G$1005,$A9,'Question Mapping'!$C$2:$C$1005,B$3) -> 0 | C9: =COUNTIFS('Question Mapping'!$G$2:$G$1005,$A9,'Question Mapping'!$C$2:$C$1005,C$3) -> 0 | D9: =COUNTIFS('Question Mapping'!$G$2:$G$1005,$A9,'Question Mapping'!$C$2:$C$1005,D$3) -> 0 | E9: =COUNTIFS('Question Mapping'!$G$2:$G$1005,$A9,'Question Mapping'!$C$2:$C$1005,E$3) -> 291 | F9: =SUM(B9:E9) -> 291
A10: Total | B10: =SUM(B4:B9) -> 630 | C10: =SUM(C4:C9) -> 41 | D10: =SUM(D4:D9) -> 42 | E10: =SUM(E4:E9) -> 291 | F10: =SUM(F4:F9) -> 1004
A12: Note: 'Other' sources (if any) are not counted in the modality columns.
